DrissionRecorder/__init__.py
DrissionRecorder/base.py
DrissionRecorder/base.pyi
DrissionRecorder/byte_recorder.py
DrissionRecorder/byte_recorder.pyi
DrissionRecorder/db_recorder.py
DrissionRecorder/db_recorder.pyi
DrissionRecorder/filler.py
DrissionRecorder/filler.pyi
DrissionRecorder/recorder.py
DrissionRecorder/recorder.pyi
DrissionRecorder/setter.py
DrissionRecorder/setter.pyI
DrissionRecorder/tools.py
DrissionRecorder/tools.pyi
DrissionRecorder/style/__init__.py
DrissionRecorder/style/cell_style.py
DrissionRecorder-3.6.2.dist-info/LICENSE
DrissionRecorder-3.6.2.dist-info/METADATA
DrissionRecorder-3.6.2.dist-info/WHEEL
DrissionRecorder-3.6.2.dist-info/top_level.txt
DrissionRecorder-3.6.2.dist-info/RECORD
