Metadata-Version: 2.1
Name: DrissionRecorder
Version: 3.6.2
Summary: 用于记录数据的模块。
Home-page: https://gitee.com/g1879/DrissionRecorder
Author: g1879
Author-email: g1879@qq.com
License: MIT
Keywords: DrissionRecorder
Classifier: Programming Language :: Python :: 3.6
Classifier: Development Status :: 4 - Beta
Classifier: Topic :: Utilities
Classifier: License :: OSI Approved :: BSD License
Requires-Python: >=3.6
License-File: LICENSE
Requires-Dist: openpyxl
